grafana_dashboard_manager/__init__.py
grafana_dashboard_manager/__main__.py
grafana_dashboard_manager/api/auth.py
grafana_dashboard_manager/api/rest_client.py
grafana_dashboard_manager/commands/__init__.py
grafana_dashboard_manager/commands/dashboard_download.py
grafana_dashboard_manager/commands/dashboard_upload.py
grafana_dashboard_manager/exceptions.py
grafana_dashboard_manager/global_config.py
grafana_dashboard_manager/grafana/__init__.py
grafana_dashboard_manager/grafana/grafana_api.py
grafana_dashboard_manager/handlers/api_dashboards.py
grafana_dashboard_manager/handlers/api_folders.py
grafana_dashboard_manager/handlers/base_handler.py
grafana_dashboard_manager/models/__init__.py
grafana_dashboard_manager/models/dashboard.py
grafana_dashboard_manager/models/folder.py
grafana_dashboard_manager/utils.py
grafana_dashboard_manager-0.2.9.92468794901.dist-info/LICENSE
grafana_dashboard_manager-0.2.9.92468794901.dist-info/METADATA
grafana_dashboard_manager-0.2.9.92468794901.dist-info/WHEEL
grafana_dashboard_manager-0.2.9.92468794901.dist-info/entry_points.txt
grafana_dashboard_manager-0.2.9.92468794901.dist-info/RECORD
