Metadata-Version: 2.1
Name: grafana_dashboard_manager
Version: 0.2.9.92468794901
Summary: A cli utility that uses Grafana's HTTP API to easily save and restore dashboards.
Home-page: https://www.beamconnectivity.com
License: MIT
Keywords: grafana,dashboard,json
Author: Vince Chan
Author-email: vince@beamconnectivity.com
Requires-Python: >=3.11,<4.0
Classifier: License :: OSI Approved :: MIT License
Classifier: Programming Language :: Python :: 3
Classifier: Programming Language :: Python :: 3.11
Classifier: Programming Language :: Python :: 3.12
Requires-Dist: httpx (>=0.27.0,<0.28.0)
Requires-Dist: pydantic (>=2.6.4,<3.0.0)
Requires-Dist: rich (>=13.7.1,<14.0.0)
Project-URL: Repository, https://github.com/Beam-Connectivity/grafana-dashboard-manager
